icanexplain/__init__.py
icanexplain/datasets/iowa_whiskey_sales.csv.zip
icanexplain/datasets/product_footprints.csv.gz
icanexplain/datasets/us_general_election_popular_vote.csv.zip
icanexplain/datasets/world_demography.csv
icanexplain/datasets.py
icanexplain/test_mean.py
icanexplain/test_sum.py
icanexplain-0.3.0.dist-info/LICENSE
icanexplain-0.3.0.dist-info/METADATA
icanexplain-0.3.0.dist-info/WHEEL
icanexplain-0.3.0.dist-info/RECORD
