Metadata-Version: 2.1
Name: icanexplain
Version: 0.3.0
Summary: Explain why metrics change by unpacking them
Author: Max Halford
Author-email: maxhalford25@gmail.com
Requires-Python: >=3.10,<4.0
Classifier: Programming Language :: Python :: 3
Classifier: Programming Language :: Python :: 3.10
Classifier: Programming Language :: Python :: 3.11
Classifier: Programming Language :: Python :: 3.12
Requires-Dist: altair (>=5.3.0,<6.0.0)
Requires-Dist: ibis-framework (>=9.5.0,<10.0.0)
